__init__.py
libWiiPy/__init__.py
libWiiPy/shared.py
libWiiPy/types.py
libWiiPy/archive/__init__.py
libWiiPy/archive/ash.py
libWiiPy/archive/u8.py
libWiiPy/nand/__init__.py
libWiiPy/nand/emunand.py
libWiiPy/nand/setting.py
libWiiPy/nand/sys.py
libWiiPy/title/__init__.py
libWiiPy/title/commonkeys.py
libWiiPy/title/content.py
libWiiPy/title/crypto.py
libWiiPy/title/iospatcher.py
libWiiPy/title/nus.py
libWiiPy/title/ticket.py
libWiiPy/title/title.py
libWiiPy/title/tmd.py
libWiiPy/title/util.py
libWiiPy/title/wad.py
libWiiPy-0.5.2.dist-info/LICENSE
libWiiPy-0.5.2.dist-info/METADATA
libWiiPy-0.5.2.dist-info/WHEEL
libWiiPy-0.5.2.dist-info/top_level.txt
libWiiPy-0.5.2.dist-info/RECORD
