Metadata-Version: 2.1
Name: libWiiPy
Version: 0.5.2
Summary: A modern Python library for handling files used by the Wii
Author-email: NinjaCheetah <ninjacheetah@ncxprogramming.com>, Lillian Skinner <lillian@randommeaninglesscharacters.com>
Project-URL: Homepage, https://github.com/NinjaCheetah/libWiiPy
Project-URL: Documentation, https://ninjacheetah.github.io/libWiiPy/
Project-URL: Repository, https://github.com/NinjaCheetah/libWiiPy.git
Project-URL: Issues, https://github.com/NinjaCheetah/libWiiPy/issues
Keywords: Wii,wii
Classifier: Development Status :: 4 - Beta
Classifier: Intended Audience :: Developers
Classifier: License :: OSI Approved :: MIT License
Classifier: Operating System :: OS Independent
Classifier: Programming Language :: Python :: 3.10
Classifier: Programming Language :: Python :: 3.11
Classifier: Programming Language :: Python :: 3.12
Requires-Python: >=3.10
License-File: LICENSE
Requires-Dist: pycryptodome
Requires-Dist: requests
